rag_server/__init__.py
rag_server/server.py
rag_server/utils/__init__.py
rag_server/utils/llm.py
rag_server/utils/vector/__init__.py
rag_server/utils/vector/misc.py
rag_server/utils/vector/store.py
rag_server-0.0.2.dist-info/METADATA
rag_server-0.0.2.dist-info/WHEEL
rag_server-0.0.2.dist-info/entry_points.txt
rag_server-0.0.2.dist-info/RECORD
