Metadata-Version: 2.4
Name: rag_server
Version: 0.0.2
Summary: A FastMCP-based RAG server for dynamic document ingestion
Project-URL: Homepage, https://github.com/synehq/mcp-hybrid-rag
Project-URL: Bug Tracker, https://github.com/synehq/mcp-hybrid-rag/issues
Author-email: SyneHQ <human@synehq.com>
License-Expression: MIT
Requires-Python: >=3.12
Requires-Dist: chromadb
Requires-Dist: faiss-cpu
Requires-Dist: fastmcp
Requires-Dist: langchain-google-genai
Requires-Dist: numpy
Requires-Dist: openai
Requires-Dist: pypdf2
Requires-Dist: python-docx
Requires-Dist: requests
Requires-Dist: six
Requires-Dist: textract-py3
Provides-Extra: dev
Requires-Dist: pytest; extra == 'dev'
